agently_sdk/__init__.py
agently_sdk/_version.py
agently_sdk/plugins/__init__.py
agently_sdk/plugins/base.py
agently_sdk/plugins/decorators.py
agently_sdk/plugins/variables.py
agently_sdk/styles/__init__.py
agently_sdk/styles/builder.py
agently_sdk/utils/__init__.py
agently_sdk/utils/testing.py
agently_sdk-0.5.2.dist-info/LICENSE
agently_sdk-0.5.2.dist-info/METADATA
agently_sdk-0.5.2.dist-info/WHEEL
agently_sdk-0.5.2.dist-info/top_level.txt
agently_sdk-0.5.2.dist-info/RECORD
