Metadata-Version: 2.2
Name: agently-sdk
Version: 0.5.2
Summary: Official SDK for developing extensions for the Agently framework
Author-email: Onward Platforms <info@onwardplatforms.com>
License: MIT
Project-URL: Homepage, https://github.com/onwardplatforms/agently-sdk
Project-URL: Bug Tracker, https://github.com/onwardplatforms/agently-sdk/issues
Project-URL: Documentation, https://github.com/onwardplatforms/agently-sdk
Keywords: agently,sdk,ai,agent,plugin
Classifier: Programming Language :: Python :: 3
Classifier: Programming Language :: Python :: 3.11
Classifier: Programming Language :: Python :: 3.12
Classifier: License :: OSI Approved :: MIT License
Classifier: Operating System :: OS Independent
Classifier: Development Status :: 4 - Beta
Classifier: Intended Audience :: Developers
Classifier: Topic :: Software Development :: Libraries :: Python Modules
Requires-Python: >=3.11
License-File: LICENSE
Requires-Dist: semantic-kernel>=0.3.0
